{
	"secondCityPassengerFlow": "石家庄",
	"forward": [{
		"statisHour": "01:00",
		"relationCnt": "904",
		"startingCity": "保定市",
		"arrivalCity": "石家庄"
	}, {
		"statisHour": "02:00",
		"relationCnt": "834",
		"startingCity": "保定市",
		"arrivalCity": "石家庄"
	}, {
		"statisHour": "03:00",
		"relationCnt": "1005",
		"startingCity": "保定市",
		"arrivalCity": "石家庄"
	}, {
		"statisHour": "04:00",
		"relationCnt": "1323",
		"startingCity": "保定市",
		"arrivalCity": "石家庄"
	}, {
		"statisHour": "05:00",
		"relationCnt": "2102",
		"startingCity": "保定市",
		"arrivalCity": "石家庄"
	}, {
		"statisHour": "06:00",
		"relationCnt": "5108",
		"startingCity": "保定市",
		"arrivalCity": "石家庄"
	}, {
		"statisHour": "07:00",
		"relationCnt": "5234",
		"startingCity": "保定市",
		"arrivalCity": "石家庄"
	}, {
		"statisHour": "08:00",
		"relationCnt": "5982",
		"startingCity": "保定市",
		"arrivalCity": "石家庄"
	}, {
		"statisHour": "09:00",
		"relationCnt": "7964",
		"startingCity": "保定市",
		"arrivalCity": "石家庄"
	}, {
		"statisHour": "10:00",
		"relationCnt": "8734",
		"startingCity": "保定市",
		"arrivalCity": "石家庄"
	}, {
		"statisHour": "11:00",
		"relationCnt": "8661",
		"startingCity": "保定市",
		"arrivalCity": "石家庄"
	}, {
		"statisHour": "12:00",
		"relationCnt": "9055",
		"startingCity": "保定市",
		"arrivalCity": "石家庄"
	}, {
		"statisHour": "13:00",
		"relationCnt": "7548",
		"startingCity": "保定市",
		"arrivalCity": "石家庄"
	}, {
		"statisHour": "14:00",
		"relationCnt": "9111",
		"startingCity": "保定市",
		"arrivalCity": "石家庄"
	}, {
		"statisHour": "15:00",
		"relationCnt": "9549",
		"startingCity": "保定市",
		"arrivalCity": "石家庄"
	}, {
		"statisHour": "16:00",
		"relationCnt": "11489",
		"startingCity": "保定市",
		"arrivalCity": "石家庄"
	}, {
		"statisHour": "17:00",
		"relationCnt": "11523",
		"startingCity": "保定市",
		"arrivalCity": "石家庄"
	}, {
		"statisHour": "18:00",
		"relationCnt": "8793",
		"startingCity": "保定市",
		"arrivalCity": "石家庄"
	}, {
		"statisHour": "19:00",
		"relationCnt": "8318",
		"startingCity": "保定市",
		"arrivalCity": "石家庄"
	}, {
		"statisHour": "20:00",
		"relationCnt": "6305",
		"startingCity": "保定市",
		"arrivalCity": "石家庄"
	}, {
		"statisHour": "21:00",
		"relationCnt": "5017",
		"startingCity": "保定市",
		"arrivalCity": "石家庄"
	}, {
		"statisHour": "22:00",
		"relationCnt": "4424",
		"startingCity": "保定市",
		"arrivalCity": "石家庄"
	}],
	"maxCityPassengerFlow": "保定市",
	"reverse": [{
		"statisHour": "01:00",
		"relationCnt": "1254",
		"startingCity": "石家庄",
		"arrivalCity": "保定市"
	}, {
		"statisHour": "02:00",
		"relationCnt": "2020",
		"startingCity": "石家庄",
		"arrivalCity": "保定市"
	}, {
		"statisHour": "03:00",
		"relationCnt": "3911",
		"startingCity": "石家庄",
		"arrivalCity": "保定市"
	}, {
		"statisHour": "04:00",
		"relationCnt": "2582",
		"startingCity": "石家庄",
		"arrivalCity": "保定市"
	}, {
		"statisHour": "05:00",
		"relationCnt": "3325",
		"startingCity": "石家庄",
		"arrivalCity": "保定市"
	}, {
		"statisHour": "06:00",
		"relationCnt": "4704",
		"startingCity": "石家庄",
		"arrivalCity": "保定市"
	}, {
		"statisHour": "07:00",
		"relationCnt": "8370",
		"startingCity": "石家庄",
		"arrivalCity": "保定市"
	}, {
		"statisHour": "08:00",
		"relationCnt": "9364",
		"startingCity": "石家庄",
		"arrivalCity": "保定市"
	}, {
		"statisHour": "09:00",
		"relationCnt": "8034",
		"startingCity": "石家庄",
		"arrivalCity": "保定市"
	}, {
		"statisHour": "10:00",
		"relationCnt": "8778",
		"startingCity": "石家庄",
		"arrivalCity": "保定市"
	}, {
		"statisHour": "11:00",
		"relationCnt": "8765",
		"startingCity": "石家庄",
		"arrivalCity": "保定市"
	}, {
		"statisHour": "12:00",
		"relationCnt": "9729",
		"startingCity": "石家庄",
		"arrivalCity": "保定市"
	}, {
		"statisHour": "13:00",
		"relationCnt": "9502",
		"startingCity": "石家庄",
		"arrivalCity": "保定市"
	}, {
		"statisHour": "14:00",
		"relationCnt": "10318",
		"startingCity": "石家庄",
		"arrivalCity": "保定市"
	}, {
		"statisHour": "15:00",
		"relationCnt": "10105",
		"startingCity": "石家庄",
		"arrivalCity": "保定市"
	}, {
		"statisHour": "16:00",
		"relationCnt": "10603",
		"startingCity": "石家庄",
		"arrivalCity": "保定市"
	}, {
		"statisHour": "17:00",
		"relationCnt": "9426",
		"startingCity": "石家庄",
		"arrivalCity": "保定市"
	}, {
		"statisHour": "18:00",
		"relationCnt": "10342",
		"startingCity": "石家庄",
		"arrivalCity": "保定市"
	}, {
		"statisHour": "19:00",
		"relationCnt": "7581",
		"startingCity": "石家庄",
		"arrivalCity": "保定市"
	}, {
		"statisHour": "20:00",
		"relationCnt": "7146",
		"startingCity": "石家庄",
		"arrivalCity": "保定市"
	}, {
		"statisHour": "21:00",
		"relationCnt": "5808",
		"startingCity": "石家庄",
		"arrivalCity": "保定市"
	}, {
		"statisHour": "22:00",
		"relationCnt": "2182",
		"startingCity": "石家庄",
		"arrivalCity": "保定市"
	}]
}